Metadata-Version: 1.1
Name: TarunSingh
Version: 0.0.1
Summary: Spark datasets match after Datacompy results
Home-page: UNKNOWN
Author: Tarun Singh
Author-email: tarunchauhan138@gmail.com
License: MIT
Keywords: Spark Dataframe comparison
Platform: UNKNOWN
Classifier: Development Status :: 5 - Production/Stable
Classifier: Intended Audience :: Education
Classifier: Operating System :: Microsoft :: Windows :: Windows 10
Classifier: License :: OSI Approved :: MIT License
Classifier: Programming Language :: Python :: 3
